{
  "from_country": "New Zealand",
  "to_country": "USA",
  "pet_type": "cat",
  "slug": "new-zealand-to-usa-cat",
  "title": "Bring a Cat from New Zealand to the USA (2026 Guide)",
  "summary": "Requirements for importing a cat from New Zealand to the United States.",
  "min_age": "No minimum for cats",
  "microchip": "ISO 11784/85 required",
  "rabies_vaccine": "Recommended",
  "quarantine": "No",
  "process_steps": [
    "Microchip the cat",
    "Obtain rabies vaccination",
    "Get health certificate from NZ licensed vet",
    "Have certificate endorsed by MPI (NZ)",
    "Arrange cargo or cabin travel"
  ],
  "required_documents": [
    "MPI-endorsed Health Certificate",
    "Rabies Vaccination Certificate",
    "Microchip Record"
  ],
  "vaccines": [
    "Rabies Vaccine (recommended)"
  ],
  "travel_methods": [
    "Cargo transport (long haul)",
    "Pet courier"
  ],
  "tips": [
    "New Zealand is rabies-free; import to USA is simpler than most countries.",
    "Long flight times mean planning for pet comfort is essential."
  ]
}